aws_polly_tts_tool/__init__.py
aws_polly_tts_tool/billing.py
aws_polly_tts_tool/cli.py
aws_polly_tts_tool/engines.py
aws_polly_tts_tool/logging_config.py
aws_polly_tts_tool/utils.py
aws_polly_tts_tool/voices.py
aws_polly_tts_tool/commands/__init__.py
aws_polly_tts_tool/commands/billing_commands.py
aws_polly_tts_tool/commands/completion_commands.py
aws_polly_tts_tool/commands/engine_commands.py
aws_polly_tts_tool/commands/info_commands.py
aws_polly_tts_tool/commands/synthesize_commands.py
aws_polly_tts_tool/commands/voice_commands.py
aws_polly_tts_tool/core/__init__.py
aws_polly_tts_tool/core/client.py
aws_polly_tts_tool/core/cost_explorer.py
aws_polly_tts_tool/core/synthesize.py
aws_polly_tts_tool-0.2.0.dist-info/METADATA
aws_polly_tts_tool-0.2.0.dist-info/WHEEL
aws_polly_tts_tool-0.2.0.dist-info/entry_points.txt
aws_polly_tts_tool-0.2.0.dist-info/licenses/LICENSE
aws_polly_tts_tool-0.2.0.dist-info/RECORD
