Metadata-Version: 2.4
Name: aws-polly-tts-tool
Version: 0.2.0
Summary: A CLI that provides TTS using Amazon Polly
Project-URL: Homepage, https://github.com/dnvriend/aws-polly-tts-tool
Project-URL: Repository, https://github.com/dnvriend/aws-polly-tts-tool
Project-URL: Issues, https://github.com/dnvriend/aws-polly-tts-tool/issues
Project-URL: Documentation, https://github.com/dnvriend/aws-polly-tts-tool#readme
Author-email: Dennis Vriend <dvriend@ilionx.com>
License: MIT
License-File: LICENSE
Keywords: audio,aws,cli,neural-voices,polly,speech-synthesis,ssml,text-to-speech,tts,voice
Classifier: Development Status :: 4 - Beta
Classifier: Environment :: Console
Classifier: Intended Audience :: Developers
Classifier: Intended Audience :: System Administrators
Classifier: License :: OSI Approved :: MIT License
Classifier: Operating System :: OS Independent
Classifier: Programming Language :: Python :: 3
Classifier: Programming Language :: Python :: 3.12
Classifier: Programming Language :: Python :: 3.13
Classifier: Topic :: Multimedia :: Sound/Audio :: Speech
Classifier: Topic :: Software Development :: Libraries :: Python Modules
Classifier: Topic :: Utilities
Classifier: Typing :: Typed
Requires-Python: >=3.12
Requires-Dist: boto3>=1.34.0
Requires-Dist: click>=8.1.7
Requires-Dist: pydub>=0.25.1
